qquery/__init__.py
qquery/command_line.py
qquery-0.6.3.dist-info/LICENSE.txt
qquery-0.6.3.dist-info/METADATA
qquery-0.6.3.dist-info/WHEEL
qquery-0.6.3.dist-info/entry_points.txt
qquery-0.6.3.dist-info/top_level.txt
qquery-0.6.3.dist-info/RECORD
